dinit_graph/__init__.py
dinit_graph/dinit_graph.py
dinit_graph/data/styles/dinit_service.yaml
dinit_graph-0.1.0.dist-info/METADATA
dinit_graph-0.1.0.dist-info/WHEEL
dinit_graph-0.1.0.dist-info/entry_points.txt
dinit_graph-0.1.0.dist-info/licenses/LICENSE
dinit_graph-0.1.0.dist-info/RECORD
