Metadata-Version: 2.4
Name: dinit-graph
Version: 0.1.0
Summary: Parse dinit service files and generate a dependency graph in hiearch YAML format
Project-URL: Homepage, https://github.com/asherikov/dinit_graph
Project-URL: Issues, https://github.com/asherikov/dinit_graph/issues
Author-email: Alexander Sherikov <asherikov@yandex.com>
License-File: LICENSE
Classifier: Development Status :: 4 - Beta
Classifier: License :: OSI Approved :: Apache Software License
Classifier: Operating System :: OS Independent
Classifier: Programming Language :: Python :: 3
Classifier: Topic :: Scientific/Engineering :: Visualization
Requires-Python: >=3.8
Requires-Dist: importlib-resources
Requires-Dist: pyyaml
